bert4keras3/__init__.py
bert4keras3/backend.py
bert4keras3/layers.py
bert4keras3/models.py
bert4keras3/ops.py
bert4keras3/snippets.py
bert4keras3/tokenizers.py
bert4keras3/transformers.py
bert4keras3/Layers_add/Attentions.py
bert4keras3/Layers_add/Embeddings.py
bert4keras3/Layers_add/FFN.py
bert4keras3/Layers_add/GP.py
bert4keras3/Layers_add/LayerNorms.py
bert4keras3/Layers_add/Rwkv_layer.py
bert4keras3/Layers_add/__init__.py
bert4keras3/Layers_add/sampler.py
bert4keras3/Models/Alberts.py
bert4keras3/Models/Berts.py
bert4keras3/Models/Deberta.py
bert4keras3/Models/GAUs.py
bert4keras3/Models/GPTs.py
bert4keras3/Models/LLamas.py
bert4keras3/Models/RWKV.py
bert4keras3/Models/Roformers.py
bert4keras3/Models/T5models.py
bert4keras3/Models/__init__.py
bert4keras3-1.6.6.dist-info/LICENSE
bert4keras3-1.6.6.dist-info/METADATA
bert4keras3-1.6.6.dist-info/WHEEL
bert4keras3-1.6.6.dist-info/top_level.txt
bert4keras3-1.6.6.dist-info/RECORD
