Metadata-Version: 2.1
Name: bert4keras3
Version: 1.6.6
Summary: load chinese pretrain model
Author: pass-lin
Author-email: 935499957@qq.com
Requires: keras
License-File: LICENSE
